components/__init__.py
components/cli.py
components/component.py
components/param.py
components-1.2.8.dist-info/LICENSE
components-1.2.8.dist-info/METADATA
components-1.2.8.dist-info/WHEEL
components-1.2.8.dist-info/top_level.txt
components-1.2.8.dist-info/RECORD
